yirage/__init__.py
yirage/_core.cpython-313-darwin.so
yirage/auto_compiler.py
yirage/core.py
yirage/global_config.py
yirage/graph_dataset.py
yirage/kernel.py
yirage/operator_registry.py
yirage/profiler.py
yirage/threadblock.py
yirage/triton_profiler.py
yirage/utils.py
yirage/version.py
yirage/visualizer.py
yirage/yica_advanced.py
yirage/yica_auto_tuner.py
yirage/yica_backend_integration.py
yirage/yica_distributed.py
yirage/yica_distributed_optimizer.py
yirage/yica_kernel_generator_demo.py
yirage/yica_llama_optimizer.py
yirage/yica_operators.cpython-313-darwin.so
yirage/yica_performance_monitor.py
yirage/yica_performance_monitor_demo.py
yirage/yica_pytorch_backend.py
yirage/yica_real_optimizer.py
yirage-1.0.5.dist-info/LICENSE
yirage-1.0.5.dist-info/METADATA
yirage-1.0.5.dist-info/WHEEL
yirage-1.0.5.dist-info/top_level.txt
yirage-1.0.5.dist-info/RECORD
