Metadata-Version: 2.2
Name: yirage
Version: 1.0.5
Summary: Yirage: A Multi-Level Superoptimizer for Tensor Algebra
Home-page: https://github.com/yirage-project/yirage
License-File: LICENSE
Dynamic: home-page
Dynamic: summary
